skfusion
