Metadata-Version: 1.1
Name: scikit-fusion
Version: 0.2.1
Summary: A Python module for data fusion built on top of factorized models.
Home-page: http://github.com/marinkaz/scikit-fusion
Author: Marinka Zitnik
Author-email: marinka.zitnik@fri.uni-lj.si
License: GPLv3
Platform: UNKNOWN
Classifier: Intended Audience :: Science/Research
Classifier: Intended Audience :: Developers
Classifier: License :: OSI Approved
Classifier: Programming Language :: Python
Classifier: Topic :: Software Development
Classifier: Topic :: Scientific/Engineering
Classifier: Topic :: Scientific/Engineering :: Artificial Intelligence
Classifier: Topic :: Scientific/Engineering :: Bio-Informatics
Classifier: Programming Language :: Python :: 2
Classifier: Programming Language :: Python :: 3
